theutil/__init__.py
theutil/args.py
theutil/logging.py
theutil/main.py
theutil/plotting.py
theutil/data/__init__.py
theutil/data/a_data_object.py
theutil/data/collection.py
theutil/data/data_file.py
theutil/data/json_file.py
theutil/data/point.py
theutil/data/time_series.py
theutil/data/vector.py
theutil/data/pathfinder/__init__.py
theutil/data/pathfinder/direction.py
theutil/data/pathfinder/doors/__init__.py
theutil/data/pathfinder/doors/door.py
theutil/data/pathfinder/doors/door_collection.py
theutil/data/pathfinder/groups/__init__.py
theutil/data/pathfinder/groups/group.py
theutil/data/pathfinder/groups/group_collection.py
theutil/data/pathfinder/measurement_regions/__init__.py
theutil/data/pathfinder/measurement_regions/measurement_region.py
theutil/data/pathfinder/measurement_regions/measurement_region_collection.py
theutil/data/pathfinder/occupants/__init__.py
theutil/data/pathfinder/occupants/occupant.py
theutil/data/pathfinder/occupants/occupant_collection.py
theutil/data/pathfinder/rooms/__init__.py
theutil/data/pathfinder/rooms/room.py
theutil/data/pathfinder/rooms/room_collection.py
theutil/data/pathfinder/summary/__init__.py
theutil/data/pathfinder/summary/summary.py
theutil/data/pathfinder/tags/__init__.py
theutil/data/pathfinder/tags/tag.py
theutil/data/pathfinder/tags/tag_collection.py
theutil/data/pathfinder/targets/__init__.py
theutil/data/pathfinder/targets/target.py
theutil/data/pathfinder/targets/target_collection.py
theutil/data/pathfinder/triggers/__init__.py
theutil/data/pathfinder/triggers/trigger.py
theutil/data/pathfinder/triggers/trigger_collection.py
theutil/models/__init__.py
theutil/models/model.py
theutil/models/fds/__init__.py
theutil/models/fds/fds.py
theutil/models/pathfinder/__init__.py
theutil/models/pathfinder/pathfinder.py
theutil/models/ventus/__init__.py
theutil/models/ventus/ventus.py
theutil-0.0.1.dist-info/METADATA
theutil-0.0.1.dist-info/WHEEL
theutil-0.0.1.dist-info/top_level.txt
theutil-0.0.1.dist-info/RECORD
